aivatar_taskpad/__init__.py
aivatar_taskpad/__version__.py
aivatar_taskpad/core.py
aivatar_taskpad/dcc_executor.py
aivatar_taskpad/logger.py
aivatar_taskpad/observer.py
aivatar_taskpad/command/__init__.py
aivatar_taskpad/command/command_handler.py
aivatar_taskpad/command/command_parser.py
aivatar_taskpad/linker/__init__.py
aivatar_taskpad/linker/capturer_linker.py
aivatar_taskpad/linker/linker_base.py
aivatar_taskpad/linker/taskpad_linker.py
aivatar_taskpad/resources/__init__.py
aivatar_taskpad/utils/__init__.py
aivatar_taskpad/utils/constants.py
aivatar_taskpad/utils/filesystem.py
aivatar_taskpad/utils/ipc.py
avatar_taskpad/__init__.py
avatar_taskpad/__version__.py
avatar_taskpad/core.py
avatar_taskpad/dcc_executor.py
avatar_taskpad/logger.py
avatar_taskpad/observer.py
avatar_taskpad/command/__init__.py
avatar_taskpad/command/command_handler.py
avatar_taskpad/command/command_parser.py
avatar_taskpad/linker/__init__.py
avatar_taskpad/linker/capturer_linker.py
avatar_taskpad/linker/linker_base.py
avatar_taskpad/linker/taskpad_linker.py
avatar_taskpad/resources/__init__.py
avatar_taskpad/resources/client/capturer/D3Dcompiler_47.dll
avatar_taskpad/resources/client/capturer/Qt5Core.dll
avatar_taskpad/resources/client/capturer/Qt5Gui.dll
avatar_taskpad/resources/client/capturer/Qt5Svg.dll
avatar_taskpad/resources/client/capturer/Qt5Widgets.dll
avatar_taskpad/resources/client/capturer/avcodec-60.dll
avatar_taskpad/resources/client/capturer/avdevice-60.dll
avatar_taskpad/resources/client/capturer/avfilter-9.dll
avatar_taskpad/resources/client/capturer/avformat-60.dll
avatar_taskpad/resources/client/capturer/avutil-58.dll
avatar_taskpad/resources/client/capturer/capturer.exe
avatar_taskpad/resources/client/capturer/libEGL.dll
avatar_taskpad/resources/client/capturer/libGLESv2.dll
avatar_taskpad/resources/client/capturer/msvcp140.dll
avatar_taskpad/resources/client/capturer/msvcp140_1.dll
avatar_taskpad/resources/client/capturer/postproc-57.dll
aivatar_taskpad-0.0.1.dist-info/METADATA
aivatar_taskpad-0.0.1.dist-info/WHEEL
aivatar_taskpad-0.0.1.dist-info/top_level.txt
aivatar_taskpad-0.0.1.dist-info/RECORD
