Metadata-Version: 2.1
Name: aivatar-taskpad
Version: 0.0.1
Home-page: https://git.woa.com/hatchertang/avatar-taskpad
Author: Hatcher Tang
Author-email: hatchertang@tencent.com
Classifier: Programming Language :: Python :: 3
Classifier: License :: OSI Approved :: MIT License
Classifier: Operating System :: OS Independent
Requires-Dist: enum34
Requires-Dist: arthub-login-widgets >=0.6.0
Requires-Dist: pyqt5-tools
